README
setup.py
mc/__init__.py
mc/ioc/__init__.py
mc/ioc/component.py
mc/ioc/dependancy_container.py
mc/ioc/required_feature.py
mc/ioc/singleton.py
mc/ioc/utils.py
mc/ioc/version.py
mc_ioc.egg-info/PKG-INFO
mc_ioc.egg-info/SOURCES.txt
mc_ioc.egg-info/dependency_links.txt
mc_ioc.egg-info/requires.txt
mc_ioc.egg-info/top_level.txt