Metadata-Version: 1.1
Name: mc-ioc
Version: 0.0.1.dev0
Summary: Python IOC Implementation
Home-page: http://menacommerce.com
Author: MENA Commerce
Author-email: accounts@menacommerce.com
License: Apache License 2.0
Keywords: IOC MC
Platform: UNKNOWN
Classifier: Development Status :: 4 - Beta
Classifier: Intended Audience :: Developers
Classifier: License :: OSI Approved :: Apache Software License
Classifier: Programming Language :: Python
Classifier: Programming Language :: Python :: 2
Classifier: Programming Language :: Python :: 2.6
Classifier: Programming Language :: Python :: 2.7
Classifier: Programming Language :: Python :: 3
Classifier: Programming Language :: Python :: 3.3
Classifier: Programming Language :: Python :: 3.4
Classifier: Programming Language :: Python :: Implementation :: PyPy
Classifier: Topic :: Software Development :: Libraries :: Python Modules
